djinn/__init__.py
djinn/__main__.py
djinn/cli.py
djinn/backends/__init__.py
djinn/backends/lmstudio.py
djinn/backends/ollama.py
djinn/backends/openai_backend.py
djinn/core/__init__.py
djinn/core/advanced.py
djinn/core/advanced_ai.py
djinn/core/ai.py
djinn/core/ai_features.py
djinn/core/aliases.py
djinn/core/architect.py
djinn/core/autofix.py
djinn/core/cheatsheets.py
djinn/core/clipboard.py
djinn/core/cloud.py
djinn/core/codebase_chat.py
djinn/core/compose.py
djinn/core/context.py
djinn/core/dataml.py
djinn/core/devops_tools.py
djinn/core/devtools.py
djinn/core/docs.py
djinn/core/engine.py
djinn/core/environment.py
djinn/core/file_tools.py
djinn/core/fun_features.py
djinn/core/games.py
djinn/core/history.py
djinn/core/intelligence.py
djinn/core/interactive.py
djinn/core/languages.py
djinn/core/learning.py
djinn/core/marketplace.py
djinn/core/mobile.py
djinn/core/models.py
djinn/core/network.py
djinn/core/notifications.py
djinn/core/package_manager.py
djinn/core/plugins.py
djinn/core/predictive.py
djinn/core/productivity.py
djinn/core/recorder.py
djinn/core/release.py
djinn/core/remaining_tools.py
djinn/core/scanner.py
djinn/core/scheduler.py
djinn/core/search.py
djinn/core/security.py
djinn/core/security_tools.py
djinn/core/specialized.py
djinn/core/stats.py
djinn/core/sync.py
djinn/core/sysadmin.py
djinn/core/update_checker.py
djinn/core/vault.py
djinn/core/visualizer.py
djinn/core/webutils.py
djinn/core/workflow.py
djinn/plugins/__init__.py
djinn/plugins/api.py
djinn/plugins/cloud.py
djinn/plugins/containers.py
djinn/plugins/database.py
djinn/plugins/development.py
djinn/plugins/files.py
djinn/plugins/git_advanced.py
djinn/plugins/misc.py
djinn/plugins/monitoring.py
djinn/plugins/networking.py
djinn/plugins/security.py
djinn/plugins/sysadmin.py
djinn/tui/__init__.py
djinn/tui/additional_features.py
djinn/tui/dashboard.py
djinn/tui/database.py
djinn/tui/file_explorer.py
djinn/tui/help_navigator.py
djinn/tui/http_client.py
djinn/tui/interactive.py
djinn_cli-2.3.3.dist-info/licenses/LICENSE
djinn_cli-2.3.3.dist-info/METADATA
djinn_cli-2.3.3.dist-info/WHEEL
djinn_cli-2.3.3.dist-info/entry_points.txt
djinn_cli-2.3.3.dist-info/top_level.txt
djinn_cli-2.3.3.dist-info/RECORD
