Metadata-Version: 2.4
Name: djinn-cli
Version: 2.3.3
Summary: AI-powered CLI that converts natural language into shell commands. Built-in tools for DevOps, Security, Development, and Productivity.
Author-email: Youssef Boubli <bbb.vloger@gmail.com>
License: MIT
Project-URL: Homepage, https://boubli.tech
Project-URL: Repository, https://github.com/boubli/djinn
Project-URL: Issues, https://github.com/boubli/djinn/issues
Keywords: cli,terminal,ai,llm,shell,commands,ollama,devops,automation
Classifier: Development Status :: 4 - Beta
Classifier: Environment :: Console
Classifier: Intended Audience :: Developers
Classifier: License :: OSI Approved :: MIT License
Classifier: Operating System :: OS Independent
Classifier: Programming Language :: Python :: 3
Classifier: Programming Language :: Python :: 3.8
Classifier: Programming Language :: Python :: 3.9
Classifier: Programming Language :: Python :: 3.10
Classifier: Programming Language :: Python :: 3.11
Classifier: Programming Language :: Python :: 3.12
Classifier: Topic :: Utilities
Requires-Python: >=3.8
License-File: LICENSE
Requires-Dist: click>=8.0
Requires-Dist: rich>=13.0
Requires-Dist: requests>=2.28
Requires-Dist: openai>=1.0
Requires-Dist: pyperclip>=1.8
Requires-Dist: prompt-toolkit>=3.0
Requires-Dist: psutil>=5.9
Provides-Extra: dev
Requires-Dist: pytest; extra == "dev"
Requires-Dist: black; extra == "dev"
Requires-Dist: ruff; extra == "dev"
Provides-Extra: full
Requires-Dist: textual>=0.40; extra == "full"
Requires-Dist: cryptography>=41.0; extra == "full"
Requires-Dist: pip-audit>=2.6; extra == "full"
Requires-Dist: qrcode>=7.4; extra == "full"
Requires-Dist: pillow>=10.0; extra == "full"
Requires-Dist: tqdm>=4.66; extra == "full"
Requires-Dist: PyPDF2>=3.0; extra == "full"
Requires-Dist: pyfiglet>=0.8; extra == "full"
Requires-Dist: dnspython>=2.4; extra == "full"
Requires-Dist: speedtest-cli>=2.1; extra == "full"
Requires-Dist: beautifulsoup4>=4.12; extra == "full"
Requires-Dist: schedule>=1.2; extra == "full"
Requires-Dist: spotipy>=2.23; extra == "full"
Requires-Dist: SpeechRecognition>=3.10; extra == "full"
Requires-Dist: pyttsx3>=2.90; extra == "full"
Provides-Extra: tui
Requires-Dist: textual>=0.40; extra == "tui"
Requires-Dist: pyfiglet>=0.8; extra == "tui"
Provides-Extra: security
Requires-Dist: cryptography>=41.0; extra == "security"
Requires-Dist: pip-audit>=2.6; extra == "security"
Provides-Extra: network
Requires-Dist: dnspython>=2.4; extra == "network"
Requires-Dist: speedtest-cli>=2.1; extra == "network"
Requires-Dist: beautifulsoup4>=4.12; extra == "network"
Provides-Extra: files
Requires-Dist: qrcode>=7.4; extra == "files"
Requires-Dist: pillow>=10.0; extra == "files"
Requires-Dist: tqdm>=4.66; extra == "files"
Requires-Dist: PyPDF2>=3.0; extra == "files"
Provides-Extra: voice
Requires-Dist: SpeechRecognition>=3.10; extra == "voice"
Requires-Dist: pyttsx3>=2.90; extra == "voice"
Provides-Extra: music
Requires-Dist: spotipy>=2.23; extra == "music"
Dynamic: license-file
